{"code":200,"msg":"success","result":{"list":[{"hotword":"樊振东英文告别主场球迷","hotwordnum":" 1069176","hottag":""},{"hotword":"法国将不义之财归还被抢掠的中国","hotwordnum":" 749310","hottag":""},{"hotword":"广交会增设智能穿戴等9大专区","hotwordnum":" 615620","hottag":""},{"hotword":"金莎孙丞潇试婚纱压价","hotwordnum":"综艺 485594","hottag":""},{"hotword":"80万开店倒闭又投40万开店小伙发声","hotwordnum":" 314023","hottag":""},{"hotword":"阚清子孙怡还没和好吗","hotwordnum":"综艺 235397","hottag":"新"},{"hotword":"智己LS8今日正式上市","hotwordnum":" ","hottag":""},{"hotword":"拜仁4比3皇马","hotwordnum":" 229252","hottag":""},{"hotword":"美军妄想威慑中国内陆","hotwordnum":" 214671","hottag":""},{"hotword":"24岁抗癌博主徐平安去世","hotwordnum":" 187760","hottag":""},{"hotword":"多条东南亚航线突然取消原因曝光","hotwordnum":" 166010","hottag":""},{"hotword":"赵子琪 是逼我爆所有的料吗","hotwordnum":"综艺 161651","hottag":"大卖"},{"hotword":"男子遭开门杀碾压身亡目击者发声","hotwordnum":" 158315","hottag":""},{"hotword":"美国将退还超1万亿元关税","hotwordnum":" 149790","hottag":"新"},{"hotword":"谈莉娜孕35周胎位不正产检落泪","hotwordnum":" 135552","hottag":""},{"hotword":"8岁女童化疗前冻存卵巢组织","hotwordnum":" 133599","hottag":"新"},{"hotword":"何润东说翻红后接到很多工作邀约","hotwordnum":"剧集 126958","hottag":""},{"hotword":"欧冠4强出炉","hotwordnum":" 122228","hottag":""},{"hotword":"赵子琪质问芒果TV","hotwordnum":" 117050","hottag":""},{"hotword":"孟子义李昀锐 等风热吻你","hotwordnum":"剧集 114218","hottag":""},{"hotword":"尹锡悦笑看金建希却惨遭无视","hotwordnum":" 113768","hottag":""},{"hotword":"何润东谈张凌赫被评粉底液将军","hotwordnum":" 113524","hottag":"新"},{"hotword":"印度3000万人要没饭吃","hotwordnum":" 113179","hottag":""},{"hotword":"伊朗美制通信设备遇袭时集体失灵","hotwordnum":" 112599","hottag":"热"},{"hotword":"乙肝抗体没了要不要补打疫苗","hotwordnum":" 111951","hottag":""},{"hotword":"被破窗取AED车辆获免费换车窗","hotwordnum":" 111427","hottag":""},{"hotword":"业内人士对肖战团队的评价","hotwordnum":"剧集 111130","hottag":""},{"hotword":"洛克王国","hotwordnum":" 110543","hottag":""},{"hotword":"被臭味yue上热搜的记者发声","hotwordnum":" 109808","hottag":""},{"hotword":"母亲喊女儿吃饭才惊觉其已遇害530天","hotwordnum":" 109125","hottag":""},{"hotword":"做家务的机器人让外国人疯狂心动","hotwordnum":" 108865","hottag":""},{"hotword":"刘耀文提到了张真源SLY乐队","hotwordnum":" 108262","hottag":""},{"hotword":"黄金大起大落","hotwordnum":" 107655","hottag":""},{"hotword":"印度裔男子假意助人实施二次性侵","hotwordnum":" 107405","hottag":"新"},{"hotword":"在德读硕中国小伙多次下药迷奸女友","hotwordnum":" 107075","hottag":""},{"hotword":"老刀99 王子杰","hotwordnum":" 106300","hottag":"新"},{"hotword":"田曦薇张凌赫庆功宴小动作","hotwordnum":"剧集 105782","hottag":""},{"hotword":"连婚纱都遮不住她的律动","hotwordnum":" 105083","hottag":""},{"hotword":"法国涉嫌非法获取文物清单将公布","hotwordnum":" 104797","hottag":""},{"hotword":"婴儿哭闹20分钟男乘客30秒哄好","hotwordnum":" 104274","hottag":""},{"hotword":"白日提灯 双结局","hotwordnum":"剧集 103825","hottag":""},{"hotword":"郑丽文返台后穿大陆定制中山装亮相","hotwordnum":" 103409","hottag":"热"},{"hotword":"当地调查B太称在大凉山帮扶被骗","hotwordnum":" 102752","hottag":""},{"hotword":"阿森纳0比0葡萄牙体育","hotwordnum":" 102172","hottag":"新"},{"hotword":"樊振东3比2伯特兰","hotwordnum":" 101970","hottag":""},{"hotword":"伊朗警告美持续封锁是破坏停火前奏","hotwordnum":" 101375","hottag":""},{"hotword":"萨尔布吕肯3比1云达不莱梅","hotwordnum":" 100531","hottag":""},{"hotword":"全国首例试管婴儿享工亡抚恤金","hotwordnum":" 100027","hottag":"新"},{"hotword":"自如老师 侵权","hotwordnum":" 99875","hottag":""},{"hotword":"这个世界总有人在缝缝补补","hotwordnum":" 99251","hottag":"新"},{"hotword":"31岁男子滑旱冰摔倒去世","hotwordnum":" 98615","hottag":""}]}}