{"code":200,"msg":"success","result":{"list":[{"hotword":"得力集团辞退跛脚员工","hotwordnum":" 1122227","hottag":"\n                                                                \n                                    \n                                \n                                                            "},{"hotword":"西贝厨师说生鸡内脏被下水道冲走了","hotwordnum":" 555749","hottag":"新"},{"hotword":"盛世中国如你所愿","hotwordnum":" 441350","hottag":"\n                                                                \n                                    \n                                \n                                                            "},{"hotword":"跟着榜单去扫街","hotwordnum":" ","hottag":""},{"hotword":"青岛保时捷女销售9月再夺销冠","hotwordnum":" 441342","hottag":"\n                                                            "},{"hotword":"国庆提前出发的大聪明已堵路上","hotwordnum":" 377142","hottag":"荐"},{"hotword":"K签增设近两月为何突然引发关注","hotwordnum":" 344077","hottag":"\n                                                                \n                                    \n                                \n                                                            "},{"hotword":"欧莱雅巴黎时装周大秀","hotwordnum":" ","hottag":""},{"hotword":"网友称因跛脚在入职当天被得力辞退","hotwordnum":" 302042","hottag":"\n                                                            "},{"hotword":"涉电诈中国女孩曾让闺蜜去埃及陪她","hotwordnum":" 255140","hottag":""},{"hotword":"日本引进5万印度人才引发抗议","hotwordnum":" 181674","hottag":"\n                                                            "},{"hotword":"泡泡玛特新品16倍溢价黄牛犯了愁","hotwordnum":" 181339","hottag":"新"},{"hotword":"李晨 短剧狗不演我演","hotwordnum":" 180934","hottag":"\n                                                                \n                                    \n                                \n                                                            "},{"hotword":"苏醒道歉","hotwordnum":" 180538","hottag":"火热"},{"hotword":"娜扎答应了我的求婚","hotwordnum":" 180198","hottag":"\n                                                                \n                                    \n                                \n                                                            "},{"hotword":"小沈阳叫沈佳润美美孩孩宝","hotwordnum":"演出 179830","hottag":"新"},{"hotword":"肖战谍报上不封顶杀青","hotwordnum":"剧集 179476","hottag":"\n                                                                \n                                    \n                                \n                                                            "},{"hotword":"佟丽娅问小酒窝朵朵般配不","hotwordnum":" 179119","hottag":""},{"hotword":"董璇妥协","hotwordnum":"综艺 178734","hottag":"\n                                                            "},{"hotword":"即将迎来Jonathan的Dior女装首秀","hotwordnum":" 178519","hottag":""},{"hotword":"孟子义李昀锐从早亲到晚","hotwordnum":"剧集 178048","hottag":"\n                                                            "},{"hotword":"终于知道她为什么叫靓靓了","hotwordnum":" 177827","hottag":"新"},{"hotword":"纤维粒 夏思齐我出来了","hotwordnum":" 177269","hottag":"\n                                                                \n                                    \n                                \n                                                            "},{"hotword":"失联6天中国女孩因涉嫌参与电诈被捕","hotwordnum":" 177038","hottag":"新"},{"hotword":"准新娘称金价再涨三金手镯变耳环","hotwordnum":" 176427","hottag":"\n                                                                \n                                    \n                                \n                                                            "},{"hotword":"千万要少吃外面的烤鱼","hotwordnum":" 176341","hottag":"热"},{"hotword":"柯爱林下车","hotwordnum":"综艺 170741","hottag":"\n                                                                \n                                    \n                                \n                                                            "},{"hotword":"徐冬冬 气血足到头顶","hotwordnum":" 163940","hottag":"新"},{"hotword":"中国K字签证要守三关","hotwordnum":" 163772","hottag":"\n                                                                \n                                    \n                                \n                                                            "},{"hotword":"肖战被摄像怼脸拍三分钟","hotwordnum":"演出 149934","hottag":"热"},{"hotword":"王一博拿到了国际D照","hotwordnum":" 149239","hottag":"\n                                                                \n                                    \n                                \n                                                            "},{"hotword":"替烈士看看今天的中国","hotwordnum":" 149198","hottag":"新"},{"hotword":"胡兵瞿颖巴黎合体","hotwordnum":" 149177","hottag":"\n                                                                \n                                    \n                                \n                                                            "},{"hotword":"孙颖莎vs朱思冰","hotwordnum":" 149176","hottag":"热"},{"hotword":"黄磊戴呼吸机睡觉","hotwordnum":"综艺 147537","hottag":"\n                                                                \n                                    \n                                \n                                                            "},{"hotword":"医院隐翅虫皮炎患者接诊量翻倍","hotwordnum":" 133963","hottag":"热"},{"hotword":"侯明昊问代拍赚多少钱一个月","hotwordnum":" 131784","hottag":"\n                                                                \n                                    \n                                \n                                                            "},{"hotword":"孙颖莎回应速胜晋级16强","hotwordnum":" 128262","hottag":"新"},{"hotword":"周也 东方红玫瑰","hotwordnum":"盛典 124160","hottag":"\n                                                                \n                                    \n                                \n                                                            "},{"hotword":"黄磊各种药不离身","hotwordnum":" 123716","hottag":"热"},{"hotword":"鸡排哥爆火后有人冒充鸡排嫂","hotwordnum":" 122275","hottag":"\n                                                                \n                                    \n                                \n                                                            "},{"hotword":"丁程鑫被自己的口误吓死了","hotwordnum":"电影 121887","hottag":""},{"hotword":"特朗普说承认巴勒斯坦国是愚蠢行为","hotwordnum":" 121743","hottag":"\n                                                            "},{"hotword":"短剧女主谈男主抛下剧组哄女友","hotwordnum":" 117707","hottag":""},{"hotword":"龚俊只是拉个手都想好怎么求婚了","hotwordnum":" 111880","hottag":"\n                                                            "},{"hotword":"普京签令 征兵13.5万人","hotwordnum":" 108470","hottag":""},{"hotword":"泡泡玛特盲盒飙到1499元遭疯抢","hotwordnum":" 107420","hottag":"\n                                                            "},{"hotword":"以总理称在加沙看不到一个消瘦的人","hotwordnum":" 105462","hottag":""},{"hotword":"易梦玲特别出演","hotwordnum":" 105306","hottag":"\n                                                            "},{"hotword":"十一放假前的状态belike","hotwordnum":" 105045","hottag":""},{"hotword":"现货黄金站上3850","hotwordnum":" 104832","hottag":"\n                                                            "},{"hotword":"孙颖莎发球被裁判提醒","hotwordnum":" 103348","hottag":"新"}]}}