{"code":200,"msg":"success","result":{"list":[{"hotword":"普京宣布与乌克兰停火条件","hotwordnum":" 191885","hottag":"\n                                                                \n                                    \n                                \n                                                            "},{"hotword":"中国男篮主场不敌韩国男篮","hotwordnum":" 174409","hottag":""},{"hotword":"我国新一代太空感知星座发布","hotwordnum":" 147319","hottag":"\n                                                            "},{"hotword":"疯狂动物城","hotwordnum":"电影 142722","hottag":""},{"hotword":"逍遥散人取消出席逆水寒赛事","hotwordnum":" 102378","hottag":"\n                                                            "},{"hotword":"香港大埔火灾已致128人遇难","hotwordnum":" 96551","hottag":""},{"hotword":"被男同学杀害女孩本子写满笔记","hotwordnum":" 95172","hottag":"\n                                                            "},{"hotword":"香港将下半旗志哀","hotwordnum":" 91564","hottag":""},{"hotword":"香港大埔火灾约200人情况未明","hotwordnum":" 89438","hottag":"\n                                                            "},{"hotword":"雷军发布小米购置税补贴重要提示","hotwordnum":" 87167","hottag":""},{"hotword":"当年真的错怪蒋欣了","hotwordnum":" 84382","hottag":"\n                                                            "},{"hotword":"微信步数 窥探隐私","hotwordnum":" 84297","hottag":""},{"hotword":"疑似范丞丞趁机表白","hotwordnum":"综艺 83686","hottag":"\n                                                            "},{"hotword":"任嘉伦成毅新剧或将对打","hotwordnum":" 83535","hottag":""},{"hotword":"当我开店取消了扫码点单","hotwordnum":" 83088","hottag":"\n                                                            "},{"hotword":"宋茜一秒看出曹骏挂脸","hotwordnum":"综艺 82573","hottag":""},{"hotword":"台政客与高市早苗办公桌合影被群嘲","hotwordnum":" 82301","hottag":"\n                                                            "},{"hotword":"女子钻漏洞下单476笔薅羊毛25万","hotwordnum":" 81851","hottag":""},{"hotword":"女子被造黄谣反被公司罚款5000元","hotwordnum":" 81263","hottag":"\n                                                            "},{"hotword":"Burberry活动怼脸生图","hotwordnum":" 80850","hottag":"热"},{"hotword":"律师解读吸毒记录封存不是彻底清除","hotwordnum":" 80821","hottag":"\n                                                                \n                                    \n                                \n                                                            "},{"hotword":"28岁确诊结肠癌晚期的真实感受","hotwordnum":" 80684","hottag":""},{"hotword":"李靓蕾现身邱泽许玮甯婚礼","hotwordnum":" 80478","hottag":"\n                                                            "},{"hotword":"湖北通报钟祥市发改局抄袭公文","hotwordnum":" 80340","hottag":""},{"hotword":"日本学者点破特朗普真实想法","hotwordnum":" 80116","hottag":"\n                                                            "},{"hotword":"姜爷爷来中国见福宝","hotwordnum":" 80030","hottag":""},{"hotword":"周姓女艺人 剧组耍大牌","hotwordnum":" 79889","hottag":"\n                                                            "},{"hotword":"一个人值不值得深交看看这件事","hotwordnum":" 79686","hottag":""},{"hotword":"华晨宇演唱会","hotwordnum":"演出 79415","hottag":"\n                                                            "},{"hotword":"逆水寒","hotwordnum":" 79282","hottag":""},{"hotword":"8张信用卡轮流还贷300万","hotwordnum":"剧集 79086","hottag":"\n                                                            "},{"hotword":"何穗产后首复工","hotwordnum":" 78944","hottag":""},{"hotword":"女子为出片生理期潜水被鲨鱼咬伤","hotwordnum":" 78809","hottag":"\n                                                            "},{"hotword":"圆明园兽首出来那一刻人麻了","hotwordnum":" 78527","hottag":""},{"hotword":"石破茂吃拉面加太多叉烧被痛骂","hotwordnum":" 78454","hottag":"\n                                                            "},{"hotword":"未来五年什么工作吃香","hotwordnum":" 78224","hottag":""},{"hotword":"戚百草的草莓发卡是杨洋自费买的","hotwordnum":"剧集 78015","hottag":"\n                                                            "},{"hotword":"爱达邮轮取消所有日本目的地","hotwordnum":" 77833","hottag":""},{"hotword":"法院向吴亦凡经纪公司追缴诉讼费","hotwordnum":" 77623","hottag":"\n                                                            "},{"hotword":"薛之谦演唱农民与土地","hotwordnum":" 77469","hottag":"热"},{"hotword":"香港廉政公署先后拘捕8人","hotwordnum":" 77336","hottag":"\n                                                                \n                                    \n                                \n                                                            "},{"hotword":"篮球名宿张长禄去世","hotwordnum":" 77036","hottag":""},{"hotword":"用杨幂打开冯太后的大女主人生","hotwordnum":" 76920","hottag":"\n                                                            "},{"hotword":"第一次在综艺里看送房产证的","hotwordnum":"综艺 76773","hottag":""},{"hotword":"融不进去的圈子就不要硬闯","hotwordnum":" 76498","hottag":"\n                                                            "},{"hotword":"俄罗斯多次对日本发出警告","hotwordnum":" 76315","hottag":""},{"hotword":"女子与老公吵架3个月患乳腺癌","hotwordnum":" 76275","hottag":"\n                                                            "},{"hotword":"周深刘宇宁二搭三搭勾勾搭搭","hotwordnum":"综艺 75950","hottag":""},{"hotword":"Zeus跟Peanut和Faker聚餐","hotwordnum":" 75857","hottag":"\n                                                            "},{"hotword":"捏捏状态","hotwordnum":" 75640","hottag":""}]}}