{"code":200,"msg":"success","result":{"list":[{"hotword":"演员何晴去世","hotwordnum":" 5112631","hottag":"\n                                                                \n                                    \n                                \n                                                            "},{"hotword":"4斤黄金凤冠展出时被毁谁来赔","hotwordnum":" 555167","hottag":""},{"hotword":"北京用未诉先办重新定义城市治理","hotwordnum":" 355723","hottag":"\n                                                            "},{"hotword":"何晴","hotwordnum":" 270087","hottag":"新"},{"hotword":"军队文职","hotwordnum":" 263561","hottag":"\n                                                                \n                                    \n                                \n                                                            "},{"hotword":"何晴被曝患脑瘤后淡出演艺圈","hotwordnum":" 249373","hottag":"沸"},{"hotword":"好友证实女教师生前发文称不想结婚","hotwordnum":" 243035","hottag":"\n                                                                \n                                    \n                                \n                                                            "},{"hotword":"韩国组合没有庆祝夺冠","hotwordnum":" 236641","hottag":"新"},{"hotword":"草莓这些年可冤死了","hotwordnum":" 223036","hottag":"\n                                                                \n                                    \n                                \n                                                            "},{"hotword":"恋与深空","hotwordnum":" 222015","hottag":"新"},{"hotword":"何晴 许亚军","hotwordnum":" 221703","hottag":"\n                                                                \n                                    \n                                \n                                                            "},{"hotword":"导演说尼克从未真正建立亲密关系","hotwordnum":"电影 220410","hottag":"新"},{"hotword":"戒掉熬夜第一步不是早睡","hotwordnum":" 219208","hottag":"\n                                                                \n                                    \n                                \n                                                            "},{"hotword":"汪苏泷 我不想录这一集了","hotwordnum":"综艺 217575","hottag":""},{"hotword":"00后好像被分成了三批","hotwordnum":" 217511","hottag":"\n                                                            "},{"hotword":"独居老人百万房产赠侄女因逾期失效","hotwordnum":" 192079","hottag":""},{"hotword":"许亚军何晴儿子不久前才亮相杂志","hotwordnum":" 190331","hottag":"\n                                                            "},{"hotword":"iPhone17中国市场卖爆","hotwordnum":" 186899","hottag":"新"},{"hotword":"不齐舞团创始人瞒着母亲做开颅手术","hotwordnum":" 164577","hottag":"\n                                                                \n                                    \n                                \n                                                            "},{"hotword":"不交物业费和交物业费的都沉默了","hotwordnum":" 162691","hottag":"热"},{"hotword":"星光大赏","hotwordnum":"盛典 160988","hottag":"\n                                                                \n                                    \n                                \n                                                            "},{"hotword":"999元买13斤咸菜","hotwordnum":" 157411","hottag":"新"},{"hotword":"王楚然1秒钟800个表情","hotwordnum":"综艺 154224","hottag":"\n                                                                \n                                    \n                                \n                                                            "},{"hotword":"汕头火灾独自逃生10岁女孩整日哭","hotwordnum":" 152652","hottag":""},{"hotword":"狙击蝴蝶程雅昭五官跟三观一样正","hotwordnum":"剧集 148631","hottag":"\n                                                            "},{"hotword":"TF家族新音抢票","hotwordnum":"演出 147878","hottag":"新"},{"hotword":"爱你老己在蓝盈莹身上具象化了","hotwordnum":" 147361","hottag":"\n                                                                \n                                    \n                                \n                                                            "},{"hotword":"曝美军在叙利亚紧急出动F16","hotwordnum":" 146519","hottag":""},{"hotword":"用放羊的星星打开双轨","hotwordnum":"剧集 145807","hottag":"\n                                                            "},{"hotword":"幂级恐惧犯了","hotwordnum":" 142448","hottag":""},{"hotword":"王一博科普亲妈点","hotwordnum":"综艺 141768","hottag":"\n                                                            "},{"hotword":"科比官方微博发了孙颖莎","hotwordnum":" 141718","hottag":"新"},{"hotword":"比亚迪胜诉龙猪网络诋毁案细节","hotwordnum":" 141549","hottag":"\n                                                                \n                                    \n                                \n                                                            "},{"hotword":"虞书欣姜暮头盔戴反了","hotwordnum":"剧集 141177","hottag":""},{"hotword":"这三位艺人就这么水灵灵跪下了","hotwordnum":"综艺 136026","hottag":"\n                                                            "},{"hotword":"中年大厂人离职后都去了哪里","hotwordnum":" 133067","hottag":""},{"hotword":"李现 故宫刺客","hotwordnum":" 118323","hottag":"\n                                                            "},{"hotword":"滑翔伞坠落致残飞行者自担八成责任","hotwordnum":" 112372","hottag":""},{"hotword":"低价社区食堂为何开不下去了","hotwordnum":" 111102","hottag":"\n                                                            "},{"hotword":"全场观众把掌声送给孙颖莎","hotwordnum":" 110534","hottag":""},{"hotword":"这一段真的有人看了不脸红吗","hotwordnum":" 110041","hottag":"\n                                                            "},{"hotword":"周柯宇回应读狙击蝴蝶剧本读到害羞","hotwordnum":"剧集 100461","hottag":"新"},{"hotword":"NBA杯半决赛","hotwordnum":" 98847","hottag":"\n                                                                \n                                    \n                                \n                                                            "},{"hotword":"成年人要有自己兜底的能力","hotwordnum":" 98133","hottag":"新"},{"hotword":"周泽昊vlog记录孙颖莎极致征程","hotwordnum":" 95373","hottag":"\n                                                                \n                                    \n                                \n                                                            "},{"hotword":"男子掀翻2学生卖糖葫芦摊位被行拘","hotwordnum":" 94178","hottag":"新"},{"hotword":"从G2到C5东升西降是大势所趋","hotwordnum":" 94027","hottag":"\n                                                                \n                                    \n                                \n                                                            "},{"hotword":"美军紧急出动F16战机","hotwordnum":" 93965","hottag":"新"},{"hotword":"新音 抢到了","hotwordnum":"演出 93701","hottag":"\n                                                                \n                                    \n                                \n                                                            "},{"hotword":"黑色长款羽绒服搭配思路","hotwordnum":" 93076","hottag":""}]}}