{"code":200,"msg":"success","result":{"list":[{"hotword":"未授权AI艺人","hotwordnum":" 2124218","hottag":""},{"hotword":"日本7.4级地震","hotwordnum":" 2093730","hottag":"新"},{"hotword":"2025年我国人均读书8.39本","hotwordnum":" 1671059","hottag":""},{"hotword":"京东中华美食大赛百万征集拿手菜","hotwordnum":" ","hottag":"新"},{"hotword":"爱奇艺 穷疯了也得有底线","hotwordnum":" 1401505","hottag":""},{"hotword":"爱奇艺疯了","hotwordnum":"综艺 18759062","hottag":"官宣"},{"hotword":"华为Pura90价格","hotwordnum":" 1072483","hottag":""},{"hotword":"五一归汉之旅","hotwordnum":" ","hottag":"新"},{"hotword":"华为发布会","hotwordnum":" 852956","hottag":""},{"hotword":"日本东北海域7.4级地震","hotwordnum":" 423974","hottag":"爆"},{"hotword":"华为pura90","hotwordnum":" 422883","hottag":""},{"hotword":"河北一地农田被曝现红色地下水","hotwordnum":" 417456","hottag":"新"},{"hotword":"低情商演员失业 高情商更多休息","hotwordnum":" 408004","hottag":""},{"hotword":"时代峰峻大楼被雷劈了","hotwordnum":" 403349","hottag":"商"},{"hotword":"买点便宜衣服穿就显年轻了","hotwordnum":" 400260","hottag":""},{"hotword":"张若昀工作室 没签过AI授权","hotwordnum":" 380593","hottag":""},{"hotword":"温峥嵘听劝回去拍戏了","hotwordnum":"综艺 372826","hottag":""},{"hotword":"爱奇艺将转型成非中心化社交媒体","hotwordnum":" 360073","hottag":"新"},{"hotword":"AI艺人库 自掘坟墓","hotwordnum":" 358564","hottag":""},{"hotword":"陈哲远丞磊曾舜晞入驻爱奇艺AI艺人库","hotwordnum":" 355695","hottag":"新"},{"hotword":"1岁男童基因突变患癌症晚期","hotwordnum":" 353213","hottag":""},{"hotword":"美媒承认中国年轻人对美国幻灭了","hotwordnum":" 349700","hottag":"新"},{"hotword":"服刑人员遭狱警虐待后身亡","hotwordnum":" 345270","hottag":""},{"hotword":"卖脸","hotwordnum":" 342734","hottag":"热"},{"hotword":"AI观众","hotwordnum":"盛典 339867","hottag":""},{"hotword":"这句话让我决定每天多喝水了","hotwordnum":" 325489","hottag":"热"},{"hotword":"秦岚少榨点果汁嗓子早好了","hotwordnum":"综艺 321296","hottag":""},{"hotword":"爱奇艺 长剧","hotwordnum":"盛典 310697","hottag":""},{"hotword":"看完你还敢咬指甲吗","hotwordnum":" 295716","hottag":""},{"hotword":"华为Pura90超清20倍长焦视频","hotwordnum":" 295322","hottag":""},{"hotword":"重点中学高三生被抓微信零钱20多万","hotwordnum":" 294796","hottag":""},{"hotword":"万达电影告别王健林时代","hotwordnum":" 294274","hottag":"新"},{"hotword":"王橹杰跳伞","hotwordnum":" 293926","hottag":""},{"hotword":"张杰就这么突然搂住了谢娜","hotwordnum":"演出 293673","hottag":"新"},{"hotword":"入职第一周vs入职一年","hotwordnum":" 242329","hottag":""},{"hotword":"龚宇skill 真人非遗","hotwordnum":" 242326","hottag":""},{"hotword":"邓紫棋患地中海贫血","hotwordnum":" 242320","hottag":""},{"hotword":"女子拆快递误甩美工刀打到同事脖颈","hotwordnum":" 242310","hottag":""},{"hotword":"橘子海","hotwordnum":" 242300","hottag":""},{"hotword":"爱奇艺AI艺人库","hotwordnum":" 242299","hottag":"新"},{"hotword":"Pura90ProMax超大底2亿长焦","hotwordnum":" 230921","hottag":""},{"hotword":"酒店好评电话追着要合适吗","hotwordnum":" 230388","hottag":"新"},{"hotword":"吴宣仪翟潇闻这跟官宣有什么区别","hotwordnum":"剧集 230046","hottag":""},{"hotword":"严浩翔7秒的part切了17次分镜","hotwordnum":"音乐 229937","hottag":""},{"hotword":"王一博28分钟连续超6台赛车","hotwordnum":" 223974","hottag":""},{"hotword":"TF四代跳伞","hotwordnum":" 219593","hottag":"新"},{"hotword":"陈哲远对接否认签署AI授权","hotwordnum":" 212198","hottag":""},{"hotword":"Gemini能登顶老君山吗","hotwordnum":" 192641","hottag":""},{"hotword":"綦美合潮牌","hotwordnum":" 192608","hottag":""},{"hotword":"儿子病危62岁大叔火车上崩溃大哭","hotwordnum":" 192295","hottag":""},{"hotword":"何润东 车代","hotwordnum":" 191932","hottag":""},{"hotword":"黄金跳水暴跌","hotwordnum":" 191724","hottag":""}]}}